django_sequential_pagination/__init__.py
django_sequential_pagination/pagination.py
django_sequential_pagination/settings.py
django_sequential_pagination/templatetags/__init__.py
django_sequential_pagination/templatetags/pagination.py
django_sequential_pagination-0.1.0.dist-info/METADATA
django_sequential_pagination-0.1.0.dist-info/WHEEL
django_sequential_pagination-0.1.0.dist-info/top_level.txt
django_sequential_pagination-0.1.0.dist-info/RECORD
