Metadata-Version: 2.1
Name: django-sequential-pagination
Version: 0.1.0
Summary: Fast sequential objects pagination for Django
Home-page: https://github.com/IlyaSemenov/django-sequential-pagination
Author: Ilya Semenov
Author-email: ilya@semenov.co
License: BSD
Platform: UNKNOWN
Requires-Dist: Django (>=1.7)
